anyserial/__about__.py
anyserial/__init__.py
anyserial/abstract.py
anyserial/bsd.py
anyserial/darwin.py
anyserial/linux.py
anyserial/posix.py
anyserial-0.1.0.dist-info/METADATA
anyserial-0.1.0.dist-info/WHEEL
anyserial-0.1.0.dist-info/licenses/LICENSE.txt
anyserial-0.1.0.dist-info/RECORD
